<annotation>
	<folder>car_roads</folder>
	<filename>Car Top View Images_ Stock Photos... (2).jpg</filename>
	<path>D:\chaitanya\projects\test_tensorflow\project_main\Sample-Images-main\car_roads\Car Top View Images_ Stock Photos... (2).jpg</path>
	<source>
		<database>Unknown</database>
	</source>
	<size>
		<width>520</width>
		<height>280</height>
		<depth>3</depth>
	</size>
	<segmented>0</segmented>
	<object>
		<name>car</name>
		<pose>Unspecified</pose>
		<truncated>0</truncated>
		<difficult>0</difficult>
		<bndbox>
			<xmin>28</xmin>
			<ymin>24</ymin>
			<xmax>508</xmax>
			<ymax>230</ymax>
		</bndbox>
	</object>
</annotation>
